[
  {
    "timestamp": "2025-12-17T15:02:05.338Z",
    "stage": "plan",
    "plan": {
      "contentType": "parody",
      "slug": "tv-intervention-infomercial",
      "files": [
        "src/tv-intervention-infomercial.html"
      ],
      "metadata": {
        "title": "TV Intervention Infomercial",
        "icon": "📺",
        "description": "satirical warning about TV addiction",
        "collection": "stories-content"
      },
      "features": [
        "Infomercial-style testimonials and warnings",
        "Exaggerated statistics and before/after scenarios",
        "Call-to-action buttons (satirical)",
        "Scroll-triggered reveal animations",
        "Noir terminal aesthetic mockup"
      ],
      "interactionPattern": "scroll",
      "notes": [
        "NOT a game - no mobile game controls needed",
        "Focus on typography and reveal animations as content scrolls",
        "Structure like classic infomercial: hook, problem, testimonials, solution, CTA",
        "Use scroll-triggered animations for dramatic reveals",
        "Satirical tone: over-the-top warnings about TV watching habits",
        "Include fake statistics, testimonials, and product pitch",
        "Buttons are decorative/satirical - not functional game controls",
        "Mobile-first: readable text sizes, touch-friendly spacing",
        "Keep HTML complete - avoid truncation",
        "Simple scroll-based interaction - no complex JavaScript needed"
      ]
    },
    "triggerSource": {
      "kind": "mention",
      "userId": "718195745160822836",
      "username": "aneventperhaps",
      "messageId": "1450865598719463544"
    },
    "userPrompt": "create a satirical infomercial that warns  about how much TV she watches"
  },
  {
    "timestamp": "2025-12-17T15:03:36.707Z",
    "stage": "build",
    "attempt": 1,
    "buildResult": {
      "files": [
        "src/tv-intervention-infomercial.html"
      ],
      "htmlLength": 20699,
      "jsLength": 0
    }
  },
  {
    "timestamp": "2025-12-17T15:03:57.276Z",
    "stage": "test",
    "attempt": 1,
    "testResult": {
      "ok": true,
      "issues": [],
      "warnings": [
        {
          "code": "INCOMPLETE_CODE",
          "message": "Code contains TODO/FIXME or placeholders",
          "severity": "warning"
        },
        {
          "code": "MINOR_STYLE_INCONSISTENCY",
          "message": "Hero section uses rgba(255, 0, 0, 0.05) background - consider using noir palette more consistently",
          "severity": "warning"
        },
        {
          "code": "GREEN_COLOR_USAGE",
          "message": "Uses #00ff00 (green) for 'after' scenarios - not in standard noir palette but acceptable for parody contrast",
          "severity": "warning"
        }
      ],
      "score": 85,
      "buildId": "1765983716488"
    }
  },
  {
    "timestamp": "2025-12-17T15:04:01.152Z",
    "stage": "scribe",
    "docs": {
      "metadata": {
        "title": "TV Intervention Infomercial",
        "icon": "📺",
        "description": "late-night hype parody",
        "collection": "stories-content"
      },
      "releaseNotes": "built TV Intervention Infomercial - check it out",
      "howToPlay": null,
      "buildId": "1765983716488"
    }
  },
  {
    "timestamp": "2025-12-17T15:04:01.875Z",
    "stage": "complete",
    "duration": "124.8s",
    "success": true
  }
]